README.txt
setup.py
flashcards/__init__.py
flashcards/__main__.py
flashcards/configure.py
flashcards/db_api.py
flashcards/flashcards.py
flashcards/quiz_csv.py
flashcards/quiz_sql.py
flashcards.egg-info/PKG-INFO
flashcards.egg-info/SOURCES.txt
flashcards.egg-info/dependency_links.txt
flashcards.egg-info/entry_points.txt
flashcards.egg-info/requires.txt
flashcards.egg-info/top_level.txt