Metadata-Version: 1.0
Name: flashcards
Version: 2.4
Summary: A simple command line flashcards utility, similar to physical flashcards.
Home-page: https://launchpad.net/pyflashcards
Author: Jose Luis Naranjo Gomez
Author-email: luisnaranjo733@hotmail.com
License: GNU GPL
Keywords: study flashcard replacement command line utility
Platform: UNKNOWN
Classifier: License :: OSI Approved :: GNU General Public License (GPL)
Classifier: Topic :: Utilities
